<?xml version="1.0" encoding="UTF-8"?>
<beans xmlns="http://www.springframework.org/schema/beans"
	xmlns:xsi="http://www.w3.org/2001/XMLSchema-instance"
	xmlns:p="http://www.springframework.org/schema/p"
	xmlns:context="http://www.springframework.org/schema/context"
	xmlns:mvc="http://www.springframework.org/schema/mvc"
	xsi:schemaLocation="
		http://www.springframework.org/schema/beans
		https://www.springframework.org/schema/beans/spring-beans.xsd
		http://www.springframework.org/schema/context
		https://www.springframework.org/schema/context/spring-context.xsd
		http://www.springframework.org/schema/mvc 
		http://www.springframework.org/schema/mvc/spring-mvc.xsd">
	<context:component-scan base-package="spring"/>
	<!-- <context:annotation-config />
 
    For reading the properties files
    <bean id="messageSource" class="org.springframework.context.support.ReloadableResourceBundleMessageSource">
        <property name="basename" value="/WEB-INF/message" />
    </bean>
 
    Locale Change Interceptor to achieve internationalization.
    <mvc:interceptors>
        <mvc:interceptor>
            <mvc:mapping path="/admin/**" />
            <bean class="org.springframework.web.servlet.i18n.LocaleChangeInterceptor">
                <property name="paramName" value="lang"></property>
            </bean>
        </mvc:interceptor>
    </mvc:interceptors>
 
    Cookie Resolver
    <bean id="localeResolver"
        class="org.springframework.web.servlet.i18n.CookieLocaleResolver">
    </bean> -->
</beans>
